exceldiffy/__init__.py
exceldiffy/comparator.py
exceldiffy-0.1.0.dist-info/licenses/LICENSE
exceldiffy-0.1.0.dist-info/METADATA
exceldiffy-0.1.0.dist-info/WHEEL
exceldiffy-0.1.0.dist-info/top_level.txt
exceldiffy-0.1.0.dist-info/RECORD
