Metadata-Version: 2.4
Name: exceldiffy
Version: 0.1.0
Summary: Compare Excel sheet columns side by side
Author-email: Israel Bosun <israelbosun1@gmail.com>
Requires-Python: >=3.7
License-File: LICENSE
Requires-Dist: pandas
Requires-Dist: numpy
Requires-Dist: XlsxWriter
Dynamic: license-file
